<Properties StartupConfiguration="{6E7ABC94-75F1-01EC-0241-54C7FFF7DA4A}|">
  <MonoDevelop.Ide.Workspace ActiveConfiguration="Debug" />
  <MonoDevelop.Ide.ItemProperties.Assembly-CSharp PreferredExecutionTarget="0439dfc8-24d0-4bd7-97f8-4575a4d1048b" />
  <MonoDevelop.Ide.DebuggingService.PinnedWatches />
  <MonoDevelop.Ide.DebuggingService.Breakpoints>
    <BreakpointStore />
  </MonoDevelop.Ide.DebuggingService.Breakpoints>
  <MultiItemStartupConfigurations />
  <MonoDevelop.Ide.Workbench ActiveDocument="Assets/scripts/Player.cs">
    <Files>
      <File FileName="Assets/scripts/Player.cs" Line="91" Column="44" />
      <File FileName="Assets/scripts/UI.cs" Line="25" Column="55" />
      <File FileName="Assets/scripts/CameraPivot.cs" Line="76" Column="30" />
      <File FileName="Assets/scripts/VentBooster.cs" />
      <File FileName="Assets/scripts/FinishPanel.cs" />
      <File FileName="Assets/scripts/speedBoost.cs" />
      <File FileName="Assets/scripts/FinishHole.cs" />
      <File FileName="Assets/scripts/MainMenu.cs" Line="59" Column="57" />
    </Files>
    <Pads>
      <Pad Id="ProjectPad">
        <State name="__root__">
          <Node name="Simply golf">
            <Node name="Assets" expanded="True">
              <Node name="scripts" expanded="True" />
            </Node>
          </Node>
        </State>
      </Pad>
    </Pads>
  </MonoDevelop.Ide.Workbench>
</Properties>